sphinx_weasyprint_builder/__init__.py
sphinx_weasyprint_builder/loghandler.py
sphinx_weasyprint_builder/weasyprint_builder.py
sphinx_weasyprint_builder/locale/fr/LC_MESSAGES/sphinx.po
sphinx_weasyprint_builder-0.1.3.dist-info/LICENSE
sphinx_weasyprint_builder-0.1.3.dist-info/LICENSE-de
sphinx_weasyprint_builder-0.1.3.dist-info/LICENSE-fr
sphinx_weasyprint_builder-0.1.3.dist-info/LICENSE-nl
sphinx_weasyprint_builder-0.1.3.dist-info/METADATA
sphinx_weasyprint_builder-0.1.3.dist-info/WHEEL
sphinx_weasyprint_builder-0.1.3.dist-info/entry_points.txt
sphinx_weasyprint_builder-0.1.3.dist-info/top_level.txt
sphinx_weasyprint_builder-0.1.3.dist-info/RECORD
