Metadata-Version: 2.1
Name: sphinx-weasyprint-builder
Version: 0.1.3
Summary: A Sphinx PDF builder using WeasyPrint
Home-page: https://procrastinator.nerv-project.eu/nerv-project/sphinx_weasyprint_builder
Author: Kujiu
Author-email: kujiu-pypi@kujiu.org
License: EUPL 1.2
Project-URL: Source, https://procrastinator.nerv-project.eu/nerv-project/sphinx_weasyprint_builder
Project-URL: Issues, https://procrastinator.nerv-project.eu/nerv-project/sphinx_weasyprint_builder/issues
Keywords: sphinx doc pdf weasyprint
Platform: UNKNOWN
Classifier: Framework :: Sphinx
Classifier: Framework :: Sphinx :: Extension
Classifier: Development Status :: 4 - Beta
Classifier: License :: OSI Approved :: European Union Public Licence 1.2 (EUPL 1.2)
Classifier: Environment :: Console
Classifier: Environment :: Web Environment
Classifier: Intended Audience :: Developers
Classifier: Programming Language :: Python :: 3
Classifier: Programming Language :: Python :: 3.6
Classifier: Programming Language :: Python :: 3.7
Classifier: Programming Language :: Python :: 3.8
Classifier: Programming Language :: Python :: 3.9
Classifier: Operating System :: OS Independent
Classifier: Topic :: Documentation
Classifier: Topic :: Software Development :: Documentation
Requires-Dist: sphinx (>=3.0.0)
Requires-Dist: WeasyPrint
Requires-Dist: bs4
